{"text": " Ah, this is for everybody who's been restored. D. Lawrence coming at you. Get up. Come on, y'all. Let's sing this song. Ah. Ooh. Got a story to tell you. Yeah. Of some things that I've been through, but I'm here. Yo, I'm here. Oh, I'm here. I like that. Had some ups, had some downs. Oh, you only knew. I'm here. Right now, I stand before you. Oh, I'm here. Uh-uh. Had to wrestle all night long. Wondering what went wrong, but I'm here. I stand here. Oh, I'm here. Thank you, Lord. Had some sunshine and some rain. Yeah. Heartache and some pain. I'm here. I'm here. Oh, I'm here. Oh, listen. My God has touched me. God touched me. He delivered me. Ah, he delivered me. He said, I'm so free. Now, my heart is mended. My heart is mended. Oh, I'm whole again. I'm whole again. You see, there's no change. No change. I'm whole indeed. Yeah, guess what? God's my liberty. I am here. God's my liberty. I'm here. Yeah. I am here. Oh, say it, y'all. I'm here today. God touched me. God touched me. Yeah, yeah, yeah. He delivered me. Oh, he set my soul. He set my soul free. Anybody free like me. My heart is mended. Anybody mended. I'm whole again. Yeah, yeah, yeah. No change. I'm whole indeed. Guess what? God's my liberty. I am here. Oh, where the spirit is, there's liberty. I am here. Yeah, yeah, yeah. I'm here. I'm here. I'm here. I'm here. I'm here. I'm here. I'm here. I'm here. I'm here. I'm here. I'm here. I like it. We have some scars. We have some scars. I am here. But I'm here. No circumstances. Still got some circumstances. I'm still here. But I'm still here. Disappointment. Yeah. I am here. Ha ha. We have some scars. But I'm here. I am here. Circumstances. Some circumstances. I'm still here. But I'm still here. Disappointment. Oh, many disappointments. Let's take it out. Oh. I am here. Say that again, y'all. I am here. With his stripes. With his stripes. I am here. Hallelujah. Hallelujah. Oh, I am here. Oh, oh, oh. I'm here. I am here. Oh, anybody here like me? I am here. Oh, with his stripes. With his stripes. I'm here. I am here. I like this part. I like this part. We have some scars. Oh, yeah. I am here. I'm here. Circumstances. Circumstances. I'm still here. I'm still here. Disappointed. Many disappointments. I am here. I am here. They have some scars. I am here. Ah, ah. Circumstances. Circumstances. I'm still here. I'm still here. Disappointment. Disappointments. I am here. Oh, we're going to take it out this time. Oh, I am here. Oh, I'm here. Yeah. I am here. Y'all better say it like you mean it. Say it like you mean it. Say it like you mean it. I am here. I am here. I am here. I am here. With his stripes. With his stripes. I am here. And the cross died. Oh, I am here. Oh, he died that we might be healed. I am here. Oh, he suffered that we might be healed. I am here. Ah, ah, ah. From the inside out. With his stripes. I am here. Oh, yeah. They have some scars. God. Ah. I am here. Circumstances. Bad love to Johnathan Nelson and Purpose. Y'all bless them. I'm still here. Disapointment. That's right. I am here. Say that again. They have some scars. I am here. Circumstances. I'm still here. Disappointment. I am here! I am here. He have some scars. I am here. Thank you.", "segments": [{"id": 0, "seek": 0, "start": 0.0, "end": 6.04, "text": " Ah, this is for everybody who's been restored.", "tokens": [50365, 2438, 11, 341, 307, 337, 2201, 567, 311, 668, 23143, 13, 50667], "temperature": 0.0, "avg_logprob": -0.3836344897262449, "compression_ratio": 1.5175879396984924, "no_speech_prob": 0.3194536566734314}, {"id": 1, "seek": 0, "start": 6.68, "end": 7.9, "text": " D. Lawrence coming at you.", "tokens": [50699, 413, 13, 22787, 1348, 412, 291, 13, 50760], "temperature": 0.0, "avg_logprob": -0.3836344897262449, "compression_ratio": 1.5175879396984924, "no_speech_prob": 0.3194536566734314}, {"id": 2, "seek": 0, "start": 8.64, "end": 9.200000000000001, "text": " Get up.", "tokens": [50797, 3240, 493, 13, 50825], "temperature": 0.0, "avg_logprob": -0.3836344897262449, "compression_ratio": 1.5175879396984924, "no_speech_prob": 0.3194536566734314}, {"id": 3, "seek": 0, "start": 9.28, "end": 9.78, "text": " Come on, y'all.", "tokens": [50829, 2492, 322, 11, 288, 6, 336, 13, 50854], "temperature": 0.0, "avg_logprob": -0.3836344897262449, "compression_ratio": 1.5175879396984924, "no_speech_prob": 0.3194536566734314}, {"id": 4, "seek": 0, "start": 9.88, "end": 10.76, "text": " Let's sing this song.", "tokens": [50859, 961, 311, 1522, 341, 2153, 13, 50903], "temperature": 0.0, "avg_logprob": -0.3836344897262449, "compression_ratio": 1.5175879396984924, "no_speech_prob": 0.3194536566734314}, {"id": 5, "seek": 0, "start": 12.22, "end": 12.56, "text": " Ah.", "tokens": [50976, 2438, 13, 50993], "temperature": 0.0, "avg_logprob": -0.3836344897262449, "compression_ratio": 1.5175879396984924, "no_speech_prob": 0.3194536566734314}, {"id": 6, "seek": 0, "start": 13.26, "end": 13.5, "text": " Ooh.", "tokens": [51028, 7951, 13, 51040], "temperature": 0.0, "avg_logprob": -0.3836344897262449, "compression_ratio": 1.5175879396984924, "no_speech_prob": 0.3194536566734314}, {"id": 7, "seek": 0, "start": 14.42, "end": 16.64, "text": " Got a story to tell you.", "tokens": [51086, 5803, 257, 1657, 281, 980, 291, 13, 51197], "temperature": 0.0, "avg_logprob": -0.3836344897262449, "compression_ratio": 1.5175879396984924, "no_speech_prob": 0.3194536566734314}, {"id": 8, "seek": 0, "start": 16.66, "end": 16.96, "text": " Yeah.", "tokens": [51198, 865, 13, 51213], "temperature": 0.0, "avg_logprob": -0.3836344897262449, "compression_ratio": 1.5175879396984924, "no_speech_prob": 0.3194536566734314}, {"id": 9, "seek": 0, "start": 17.080000000000002, "end": 20.26, "text": " Of some things that I've been through, but I'm here.", "tokens": [51219, 2720, 512, 721, 300, 286, 600, 668, 807, 11, 457, 286, 478, 510, 13, 51378], "temperature": 0.0, "avg_logprob": -0.3836344897262449, "compression_ratio": 1.5175879396984924, "no_speech_prob": 0.3194536566734314}, {"id": 10, "seek": 0, "start": 20.6, "end": 21.400000000000002, "text": " Yo, I'm here.", "tokens": [51395, 7616, 11, 286, 478, 510, 13, 51435], "temperature": 0.0, "avg_logprob": -0.3836344897262449, "compression_ratio": 1.5175879396984924, "no_speech_prob": 0.3194536566734314}, {"id": 11, "seek": 0, "start": 22.12, "end": 23.32, "text": " Oh, I'm here.", "tokens": [51471, 876, 11, 286, 478, 510, 13, 51531], "temperature": 0.0, "avg_logprob": -0.3836344897262449, "compression_ratio": 1.5175879396984924, "no_speech_prob": 0.3194536566734314}, {"id": 12, "seek": 0, "start": 23.32, "end": 24.44, "text": " I like that.", "tokens": [51531, 286, 411, 300, 13, 51587], "temperature": 0.0, "avg_logprob": -0.3836344897262449, "compression_ratio": 1.5175879396984924, "no_speech_prob": 0.3194536566734314}, {"id": 13, "seek": 0, "start": 24.76, "end": 27.02, "text": " Had some ups, had some downs.", "tokens": [51603, 12298, 512, 15497, 11, 632, 512, 21554, 13, 51716], "temperature": 0.0, "avg_logprob": -0.3836344897262449, "compression_ratio": 1.5175879396984924, "no_speech_prob": 0.3194536566734314}, {"id": 14, "seek": 0, "start": 27.04, "end": 27.96, "text": " Oh, you only knew.", "tokens": [51717, 876, 11, 291, 787, 2586, 13, 51763], "temperature": 0.0, "avg_logprob": -0.3836344897262449, "compression_ratio": 1.5175879396984924, "no_speech_prob": 0.3194536566734314}, {"id": 15, "seek": 2796, "start": 27.96, "end": 30.54, "text": " I'm here.", "tokens": [50365, 286, 478, 510, 13, 50494], "temperature": 0.0, "avg_logprob": -0.41153725455789003, "compression_ratio": 1.7393617021276595, "no_speech_prob": 0.0002868457231670618}, {"id": 16, "seek": 2796, "start": 30.76, "end": 32.3, "text": " Right now, I stand before you.", "tokens": [50505, 1779, 586, 11, 286, 1463, 949, 291, 13, 50582], "temperature": 0.0, "avg_logprob": -0.41153725455789003, "compression_ratio": 1.7393617021276595, "no_speech_prob": 0.0002868457231670618}, {"id": 17, "seek": 2796, "start": 32.4, "end": 33.38, "text": " Oh, I'm here.", "tokens": [50587, 876, 11, 286, 478, 510, 13, 50636], "temperature": 0.0, "avg_logprob": -0.41153725455789003, "compression_ratio": 1.7393617021276595, "no_speech_prob": 0.0002868457231670618}, {"id": 18, "seek": 2796, "start": 34.0, "end": 34.34, "text": " Uh-uh.", "tokens": [50667, 4019, 12, 3232, 13, 50684], "temperature": 0.0, "avg_logprob": -0.41153725455789003, "compression_ratio": 1.7393617021276595, "no_speech_prob": 0.0002868457231670618}, {"id": 19, "seek": 2796, "start": 34.94, "end": 37.14, "text": " Had to wrestle all night long.", "tokens": [50714, 12298, 281, 43251, 439, 1818, 938, 13, 50824], "temperature": 0.0, "avg_logprob": -0.41153725455789003, "compression_ratio": 1.7393617021276595, "no_speech_prob": 0.0002868457231670618}, {"id": 20, "seek": 2796, "start": 38.08, "end": 40.760000000000005, "text": " Wondering what went wrong, but I'm here.", "tokens": [50871, 343, 684, 1794, 437, 1437, 2085, 11, 457, 286, 478, 510, 13, 51005], "temperature": 0.0, "avg_logprob": -0.41153725455789003, "compression_ratio": 1.7393617021276595, "no_speech_prob": 0.0002868457231670618}, {"id": 21, "seek": 2796, "start": 41.160000000000004, "end": 42.06, "text": " I stand here.", "tokens": [51025, 286, 1463, 510, 13, 51070], "temperature": 0.0, "avg_logprob": -0.41153725455789003, "compression_ratio": 1.7393617021276595, "no_speech_prob": 0.0002868457231670618}, {"id": 22, "seek": 2796, "start": 42.6, "end": 43.86, "text": " Oh, I'm here.", "tokens": [51097, 876, 11, 286, 478, 510, 13, 51160], "temperature": 0.0, "avg_logprob": -0.41153725455789003, "compression_ratio": 1.7393617021276595, "no_speech_prob": 0.0002868457231670618}, {"id": 23, "seek": 2796, "start": 44.16, "end": 44.88, "text": " Thank you, Lord.", "tokens": [51175, 1044, 291, 11, 3257, 13, 51211], "temperature": 0.0, "avg_logprob": -0.41153725455789003, "compression_ratio": 1.7393617021276595, "no_speech_prob": 0.0002868457231670618}, {"id": 24, "seek": 2796, "start": 44.980000000000004, "end": 47.5, "text": " Had some sunshine and some rain.", "tokens": [51216, 12298, 512, 25219, 293, 512, 4830, 13, 51342], "temperature": 0.0, "avg_logprob": -0.41153725455789003, "compression_ratio": 1.7393617021276595, "no_speech_prob": 0.0002868457231670618}, {"id": 25, "seek": 2796, "start": 47.5, "end": 47.8, "text": " Yeah.", "tokens": [51342, 865, 13, 51357], "temperature": 0.0, "avg_logprob": -0.41153725455789003, "compression_ratio": 1.7393617021276595, "no_speech_prob": 0.0002868457231670618}, {"id": 26, "seek": 2796, "start": 48.400000000000006, "end": 50.32, "text": " Heartache and some pain.", "tokens": [51387, 13569, 6000, 293, 512, 1822, 13, 51483], "temperature": 0.0, "avg_logprob": -0.41153725455789003, "compression_ratio": 1.7393617021276595, "no_speech_prob": 0.0002868457231670618}, {"id": 27, "seek": 2796, "start": 50.34, "end": 51.06, "text": " I'm here.", "tokens": [51484, 286, 478, 510, 13, 51520], "temperature": 0.0, "avg_logprob": -0.41153725455789003, "compression_ratio": 1.7393617021276595, "no_speech_prob": 0.0002868457231670618}, {"id": 28, "seek": 2796, "start": 51.400000000000006, "end": 51.96, "text": " I'm here.", "tokens": [51537, 286, 478, 510, 13, 51565], "temperature": 0.0, "avg_logprob": -0.41153725455789003, "compression_ratio": 1.7393617021276595, "no_speech_prob": 0.0002868457231670618}, {"id": 29, "seek": 2796, "start": 52.7, "end": 53.78, "text": " Oh, I'm here.", "tokens": [51602, 876, 11, 286, 478, 510, 13, 51656], "temperature": 0.0, "avg_logprob": -0.41153725455789003, "compression_ratio": 1.7393617021276595, "no_speech_prob": 0.0002868457231670618}, {"id": 30, "seek": 2796, "start": 53.8, "end": 54.28, "text": " Oh, listen.", "tokens": [51657, 876, 11, 2140, 13, 51681], "temperature": 0.0, "avg_logprob": -0.41153725455789003, "compression_ratio": 1.7393617021276595, "no_speech_prob": 0.0002868457231670618}, {"id": 31, "seek": 2796, "start": 54.8, "end": 56.58, "text": " My God has touched me.", "tokens": [51707, 1222, 1265, 575, 9828, 385, 13, 51796], "temperature": 0.0, "avg_logprob": -0.41153725455789003, "compression_ratio": 1.7393617021276595, "no_speech_prob": 0.0002868457231670618}, {"id": 32, "seek": 2796, "start": 56.6, "end": 57.66, "text": " God touched me.", "tokens": [51797, 1265, 9828, 385, 13, 51850], "temperature": 0.0, "avg_logprob": -0.41153725455789003, "compression_ratio": 1.7393617021276595, "no_speech_prob": 0.0002868457231670618}, {"id": 33, "seek": 5796, "start": 57.96, "end": 59.08, "text": " He delivered me.", "tokens": [50365, 634, 10144, 385, 13, 50421], "temperature": 0.0, "avg_logprob": -0.4406602704847181, "compression_ratio": 1.9, "no_speech_prob": 0.0010806216159835458}, {"id": 34, "seek": 5796, "start": 59.08, "end": 60.28, "text": " Ah, he delivered me.", "tokens": [50421, 2438, 11, 415, 10144, 385, 13, 50481], "temperature": 0.0, "avg_logprob": -0.4406602704847181, "compression_ratio": 1.9, "no_speech_prob": 0.0010806216159835458}, {"id": 35, "seek": 5796, "start": 60.28, "end": 63.660000000000004, "text": " He said, I'm so free.", "tokens": [50481, 634, 848, 11, 286, 478, 370, 1737, 13, 50650], "temperature": 0.0, "avg_logprob": -0.4406602704847181, "compression_ratio": 1.9, "no_speech_prob": 0.0010806216159835458}, {"id": 36, "seek": 5796, "start": 63.68, "end": 65.02, "text": " Now, my heart is mended.", "tokens": [50651, 823, 11, 452, 1917, 307, 275, 3502, 13, 50718], "temperature": 0.0, "avg_logprob": -0.4406602704847181, "compression_ratio": 1.9, "no_speech_prob": 0.0010806216159835458}, {"id": 37, "seek": 5796, "start": 65.12, "end": 66.56, "text": " My heart is mended.", "tokens": [50723, 1222, 1917, 307, 275, 3502, 13, 50795], "temperature": 0.0, "avg_logprob": -0.4406602704847181, "compression_ratio": 1.9, "no_speech_prob": 0.0010806216159835458}, {"id": 38, "seek": 5796, "start": 66.6, "end": 67.98, "text": " Oh, I'm whole again.", "tokens": [50797, 876, 11, 286, 478, 1379, 797, 13, 50866], "temperature": 0.0, "avg_logprob": -0.4406602704847181, "compression_ratio": 1.9, "no_speech_prob": 0.0010806216159835458}, {"id": 39, "seek": 5796, "start": 68.22, "end": 69.56, "text": " I'm whole again.", "tokens": [50878, 286, 478, 1379, 797, 13, 50945], "temperature": 0.0, "avg_logprob": -0.4406602704847181, "compression_ratio": 1.9, "no_speech_prob": 0.0010806216159835458}, {"id": 40, "seek": 5796, "start": 69.76, "end": 71.14, "text": " You see, there's no change.", "tokens": [50955, 509, 536, 11, 456, 311, 572, 1319, 13, 51024], "temperature": 0.0, "avg_logprob": -0.4406602704847181, "compression_ratio": 1.9, "no_speech_prob": 0.0010806216159835458}, {"id": 41, "seek": 5796, "start": 71.14, "end": 71.64, "text": " No change.", "tokens": [51024, 883, 1319, 13, 51049], "temperature": 0.0, "avg_logprob": -0.4406602704847181, "compression_ratio": 1.9, "no_speech_prob": 0.0010806216159835458}, {"id": 42, "seek": 5796, "start": 71.86, "end": 73.82000000000001, "text": " I'm whole indeed.", "tokens": [51060, 286, 478, 1379, 6451, 13, 51158], "temperature": 0.0, "avg_logprob": -0.4406602704847181, "compression_ratio": 1.9, "no_speech_prob": 0.0010806216159835458}, {"id": 43, "seek": 5796, "start": 73.84, "end": 74.74000000000001, "text": " Yeah, guess what?", "tokens": [51159, 865, 11, 2041, 437, 30, 51204], "temperature": 0.0, "avg_logprob": -0.4406602704847181, "compression_ratio": 1.9, "no_speech_prob": 0.0010806216159835458}, {"id": 44, "seek": 5796, "start": 74.98, "end": 75.96000000000001, "text": " God's my liberty.", "tokens": [51216, 1265, 311, 452, 22849, 13, 51265], "temperature": 0.0, "avg_logprob": -0.4406602704847181, "compression_ratio": 1.9, "no_speech_prob": 0.0010806216159835458}, {"id": 45, "seek": 5796, "start": 76.32, "end": 77.72, "text": " I am here.", "tokens": [51283, 286, 669, 510, 13, 51353], "temperature": 0.0, "avg_logprob": -0.4406602704847181, "compression_ratio": 1.9, "no_speech_prob": 0.0010806216159835458}, {"id": 46, "seek": 5796, "start": 78.02, "end": 78.74000000000001, "text": " God's my liberty.", "tokens": [51368, 1265, 311, 452, 22849, 13, 51404], "temperature": 0.0, "avg_logprob": -0.4406602704847181, "compression_ratio": 1.9, "no_speech_prob": 0.0010806216159835458}, {"id": 47, "seek": 5796, "start": 79.16, "end": 79.84, "text": " I'm here.", "tokens": [51425, 286, 478, 510, 13, 51459], "temperature": 0.0, "avg_logprob": -0.4406602704847181, "compression_ratio": 1.9, "no_speech_prob": 0.0010806216159835458}, {"id": 48, "seek": 5796, "start": 80.44, "end": 81.0, "text": " Yeah.", "tokens": [51489, 865, 13, 51517], "temperature": 0.0, "avg_logprob": -0.4406602704847181, "compression_ratio": 1.9, "no_speech_prob": 0.0010806216159835458}, {"id": 49, "seek": 5796, "start": 81.68, "end": 82.9, "text": " I am here.", "tokens": [51551, 286, 669, 510, 13, 51612], "temperature": 0.0, "avg_logprob": -0.4406602704847181, "compression_ratio": 1.9, "no_speech_prob": 0.0010806216159835458}, {"id": 50, "seek": 5796, "start": 82.92, "end": 83.68, "text": " Oh, say it, y'all.", "tokens": [51613, 876, 11, 584, 309, 11, 288, 6, 336, 13, 51651], "temperature": 0.0, "avg_logprob": -0.4406602704847181, "compression_ratio": 1.9, "no_speech_prob": 0.0010806216159835458}, {"id": 51, "seek": 5796, "start": 84.58, "end": 86.6, "text": " I'm here today.", "tokens": [51696, 286, 478, 510, 965, 13, 51797], "temperature": 0.0, "avg_logprob": -0.4406602704847181, "compression_ratio": 1.9, "no_speech_prob": 0.0010806216159835458}, {"id": 52, "seek": 5796, "start": 86.6, "end": 87.6, "text": " God touched me.", "tokens": [51797, 1265, 9828, 385, 13, 51847], "temperature": 0.0, "avg_logprob": -0.4406602704847181, "compression_ratio": 1.9, "no_speech_prob": 0.0010806216159835458}, {"id": 53, "seek": 8796, "start": 87.96, "end": 89.96, "text": " God touched me.", "tokens": [50365, 1265, 9828, 385, 13, 50465], "temperature": 0.4, "avg_logprob": -0.4778177272008118, "compression_ratio": 2.2010869565217392, "no_speech_prob": 0.001779255224391818}, {"id": 54, "seek": 8796, "start": 89.96, "end": 91.02, "text": " Yeah, yeah, yeah.", "tokens": [50465, 865, 11, 1338, 11, 1338, 13, 50518], "temperature": 0.4, "avg_logprob": -0.4778177272008118, "compression_ratio": 2.2010869565217392, "no_speech_prob": 0.001779255224391818}, {"id": 55, "seek": 8796, "start": 91.3, "end": 92.36, "text": " He delivered me.", "tokens": [50532, 634, 10144, 385, 13, 50585], "temperature": 0.4, "avg_logprob": -0.4778177272008118, "compression_ratio": 2.2010869565217392, "no_speech_prob": 0.001779255224391818}, {"id": 56, "seek": 8796, "start": 92.36, "end": 93.88, "text": " Oh, he set my soul.", "tokens": [50585, 876, 11, 415, 992, 452, 5133, 13, 50661], "temperature": 0.4, "avg_logprob": -0.4778177272008118, "compression_ratio": 2.2010869565217392, "no_speech_prob": 0.001779255224391818}, {"id": 57, "seek": 8796, "start": 93.91999999999999, "end": 96.97999999999999, "text": " He set my soul free.", "tokens": [50663, 634, 992, 452, 5133, 1737, 13, 50816], "temperature": 0.4, "avg_logprob": -0.4778177272008118, "compression_ratio": 2.2010869565217392, "no_speech_prob": 0.001779255224391818}, {"id": 58, "seek": 8796, "start": 96.97999999999999, "end": 98.36, "text": " Anybody free like me.", "tokens": [50816, 19082, 1737, 411, 385, 13, 50885], "temperature": 0.4, "avg_logprob": -0.4778177272008118, "compression_ratio": 2.2010869565217392, "no_speech_prob": 0.001779255224391818}, {"id": 59, "seek": 8796, "start": 98.41999999999999, "end": 100.05999999999999, "text": " My heart is mended.", "tokens": [50888, 1222, 1917, 307, 275, 3502, 13, 50970], "temperature": 0.4, "avg_logprob": -0.4778177272008118, "compression_ratio": 2.2010869565217392, "no_speech_prob": 0.001779255224391818}, {"id": 60, "seek": 8796, "start": 100.25999999999999, "end": 101.36, "text": " Anybody mended.", "tokens": [50980, 19082, 275, 3502, 13, 51035], "temperature": 0.4, "avg_logprob": -0.4778177272008118, "compression_ratio": 2.2010869565217392, "no_speech_prob": 0.001779255224391818}, {"id": 61, "seek": 8796, "start": 101.6, "end": 102.78, "text": " I'm whole again.", "tokens": [51047, 286, 478, 1379, 797, 13, 51106], "temperature": 0.4, "avg_logprob": -0.4778177272008118, "compression_ratio": 2.2010869565217392, "no_speech_prob": 0.001779255224391818}, {"id": 62, "seek": 8796, "start": 103.17999999999999, "end": 104.03999999999999, "text": " Yeah, yeah, yeah.", "tokens": [51126, 865, 11, 1338, 11, 1338, 13, 51169], "temperature": 0.4, "avg_logprob": -0.4778177272008118, "compression_ratio": 2.2010869565217392, "no_speech_prob": 0.001779255224391818}, {"id": 63, "seek": 8796, "start": 104.13999999999999, "end": 104.94, "text": " No change.", "tokens": [51174, 883, 1319, 13, 51214], "temperature": 0.4, "avg_logprob": -0.4778177272008118, "compression_ratio": 2.2010869565217392, "no_speech_prob": 0.001779255224391818}, {"id": 64, "seek": 8796, "start": 105.16, "end": 107.1, "text": " I'm whole indeed.", "tokens": [51225, 286, 478, 1379, 6451, 13, 51322], "temperature": 0.4, "avg_logprob": -0.4778177272008118, "compression_ratio": 2.2010869565217392, "no_speech_prob": 0.001779255224391818}, {"id": 65, "seek": 8796, "start": 107.52, "end": 108.17999999999999, "text": " Guess what?", "tokens": [51343, 17795, 437, 30, 51376], "temperature": 0.4, "avg_logprob": -0.4778177272008118, "compression_ratio": 2.2010869565217392, "no_speech_prob": 0.001779255224391818}, {"id": 66, "seek": 8796, "start": 108.32, "end": 109.28, "text": " God's my liberty.", "tokens": [51383, 1265, 311, 452, 22849, 13, 51431], "temperature": 0.4, "avg_logprob": -0.4778177272008118, "compression_ratio": 2.2010869565217392, "no_speech_prob": 0.001779255224391818}, {"id": 67, "seek": 8796, "start": 109.69999999999999, "end": 111.38, "text": " I am here.", "tokens": [51452, 286, 669, 510, 13, 51536], "temperature": 0.4, "avg_logprob": -0.4778177272008118, "compression_ratio": 2.2010869565217392, "no_speech_prob": 0.001779255224391818}, {"id": 68, "seek": 8796, "start": 111.39999999999999, "end": 113.28, "text": " Oh, where the spirit is, there's liberty.", "tokens": [51537, 876, 11, 689, 264, 3797, 307, 11, 456, 311, 22849, 13, 51631], "temperature": 0.4, "avg_logprob": -0.4778177272008118, "compression_ratio": 2.2010869565217392, "no_speech_prob": 0.001779255224391818}, {"id": 69, "seek": 8796, "start": 114.66, "end": 115.96, "text": " I am here.", "tokens": [51700, 286, 669, 510, 13, 51765], "temperature": 0.4, "avg_logprob": -0.4778177272008118, "compression_ratio": 2.2010869565217392, "no_speech_prob": 0.001779255224391818}, {"id": 70, "seek": 8796, "start": 115.96, "end": 117.17999999999999, "text": " Yeah, yeah, yeah.", "tokens": [51765, 865, 11, 1338, 11, 1338, 13, 51826], "temperature": 0.4, "avg_logprob": -0.4778177272008118, "compression_ratio": 2.2010869565217392, "no_speech_prob": 0.001779255224391818}, {"id": 71, "seek": 8796, "start": 117.17999999999999, "end": 117.22, "text": " I'm here.", "tokens": [51826, 286, 478, 510, 13, 51828], "temperature": 0.4, "avg_logprob": -0.4778177272008118, "compression_ratio": 2.2010869565217392, "no_speech_prob": 0.001779255224391818}, {"id": 72, "seek": 8796, "start": 117.22, "end": 117.28, "text": " I'm here.", "tokens": [51828, 286, 478, 510, 13, 51831], "temperature": 0.4, "avg_logprob": -0.4778177272008118, "compression_ratio": 2.2010869565217392, "no_speech_prob": 0.001779255224391818}, {"id": 73, "seek": 8796, "start": 117.28, "end": 117.32, "text": " I'm here.", "tokens": [51831, 286, 478, 510, 13, 51833], "temperature": 0.4, "avg_logprob": -0.4778177272008118, "compression_ratio": 2.2010869565217392, "no_speech_prob": 0.001779255224391818}, {"id": 74, "seek": 8796, "start": 117.32, "end": 117.47999999999999, "text": " I'm here.", "tokens": [51833, 286, 478, 510, 13, 51841], "temperature": 0.4, "avg_logprob": -0.4778177272008118, "compression_ratio": 2.2010869565217392, "no_speech_prob": 0.001779255224391818}, {"id": 75, "seek": 8796, "start": 117.47999999999999, "end": 117.56, "text": " I'm here.", "tokens": [51841, 286, 478, 510, 13, 51845], "temperature": 0.4, "avg_logprob": -0.4778177272008118, "compression_ratio": 2.2010869565217392, "no_speech_prob": 0.001779255224391818}, {"id": 76, "seek": 8796, "start": 117.56, "end": 117.6, "text": " I'm here.", "tokens": [51845, 286, 478, 510, 13, 51847], "temperature": 0.4, "avg_logprob": -0.4778177272008118, "compression_ratio": 2.2010869565217392, "no_speech_prob": 0.001779255224391818}, {"id": 77, "seek": 8796, "start": 117.6, "end": 117.61999999999999, "text": " I'm here.", "tokens": [51847, 286, 478, 510, 13, 51848], "temperature": 0.4, "avg_logprob": -0.4778177272008118, "compression_ratio": 2.2010869565217392, "no_speech_prob": 0.001779255224391818}, {"id": 78, "seek": 8796, "start": 117.61999999999999, "end": 117.74, "text": " I'm here.", "tokens": [51848, 286, 478, 510, 13, 51854], "temperature": 0.4, "avg_logprob": -0.4778177272008118, "compression_ratio": 2.2010869565217392, "no_speech_prob": 0.001779255224391818}, {"id": 79, "seek": 11796, "start": 117.96, "end": 118.33999999999999, "text": " I'm here.", "tokens": [50365, 286, 478, 510, 13, 50384], "temperature": 1.0, "avg_logprob": -0.9763990548940805, "compression_ratio": 2.6940298507462686, "no_speech_prob": 0.0009540353785268962}, {"id": 80, "seek": 11796, "start": 118.33999999999999, "end": 118.82, "text": " I'm here.", "tokens": [50384, 286, 478, 510, 13, 50408], "temperature": 1.0, "avg_logprob": -0.9763990548940805, "compression_ratio": 2.6940298507462686, "no_speech_prob": 0.0009540353785268962}, {"id": 81, "seek": 11796, "start": 119.6, "end": 119.61999999999999, "text": " I'm here.", "tokens": [50447, 286, 478, 510, 13, 50448], "temperature": 1.0, "avg_logprob": -0.9763990548940805, "compression_ratio": 2.6940298507462686, "no_speech_prob": 0.0009540353785268962}, {"id": 82, "seek": 11796, "start": 119.64, "end": 120.24, "text": " I like it.", "tokens": [50449, 286, 411, 309, 13, 50479], "temperature": 1.0, "avg_logprob": -0.9763990548940805, "compression_ratio": 2.6940298507462686, "no_speech_prob": 0.0009540353785268962}, {"id": 83, "seek": 11796, "start": 121.14, "end": 122.86, "text": " We have some scars.", "tokens": [50524, 492, 362, 512, 31353, 13, 50610], "temperature": 1.0, "avg_logprob": -0.9763990548940805, "compression_ratio": 2.6940298507462686, "no_speech_prob": 0.0009540353785268962}, {"id": 84, "seek": 11796, "start": 122.86, "end": 124.25999999999999, "text": " We have some scars.", "tokens": [50610, 492, 362, 512, 31353, 13, 50680], "temperature": 1.0, "avg_logprob": -0.9763990548940805, "compression_ratio": 2.6940298507462686, "no_speech_prob": 0.0009540353785268962}, {"id": 85, "seek": 11796, "start": 124.3, "end": 125.52, "text": " I am here.", "tokens": [50682, 286, 669, 510, 13, 50743], "temperature": 1.0, "avg_logprob": -0.9763990548940805, "compression_ratio": 2.6940298507462686, "no_speech_prob": 0.0009540353785268962}, {"id": 86, "seek": 11796, "start": 125.67999999999999, "end": 126.25999999999999, "text": " But I'm here.", "tokens": [50751, 583, 286, 478, 510, 13, 50780], "temperature": 1.0, "avg_logprob": -0.9763990548940805, "compression_ratio": 2.6940298507462686, "no_speech_prob": 0.0009540353785268962}, {"id": 87, "seek": 11796, "start": 126.25999999999999, "end": 127.89999999999999, "text": " No circumstances.", "tokens": [50780, 883, 9121, 13, 50862], "temperature": 1.0, "avg_logprob": -0.9763990548940805, "compression_ratio": 2.6940298507462686, "no_speech_prob": 0.0009540353785268962}, {"id": 88, "seek": 11796, "start": 127.89999999999999, "end": 128.98, "text": " Still got some circumstances.", "tokens": [50862, 8291, 658, 512, 9121, 13, 50916], "temperature": 1.0, "avg_logprob": -0.9763990548940805, "compression_ratio": 2.6940298507462686, "no_speech_prob": 0.0009540353785268962}, {"id": 89, "seek": 11796, "start": 128.98, "end": 130.48, "text": " I'm still here.", "tokens": [50916, 286, 478, 920, 510, 13, 50991], "temperature": 1.0, "avg_logprob": -0.9763990548940805, "compression_ratio": 2.6940298507462686, "no_speech_prob": 0.0009540353785268962}, {"id": 90, "seek": 11796, "start": 130.48, "end": 131.76, "text": " But I'm still here.", "tokens": [50991, 583, 286, 478, 920, 510, 13, 51055], "temperature": 1.0, "avg_logprob": -0.9763990548940805, "compression_ratio": 2.6940298507462686, "no_speech_prob": 0.0009540353785268962}, {"id": 91, "seek": 11796, "start": 131.76, "end": 134.04, "text": " Disappointment.", "tokens": [51055, 4208, 1746, 3600, 518, 13, 51169], "temperature": 1.0, "avg_logprob": -0.9763990548940805, "compression_ratio": 2.6940298507462686, "no_speech_prob": 0.0009540353785268962}, {"id": 92, "seek": 11796, "start": 134.04, "end": 134.2, "text": " Yeah.", "tokens": [51169, 865, 13, 51177], "temperature": 1.0, "avg_logprob": -0.9763990548940805, "compression_ratio": 2.6940298507462686, "no_speech_prob": 0.0009540353785268962}, {"id": 93, "seek": 11796, "start": 134.2, "end": 135.78, "text": " I am here.", "tokens": [51177, 286, 669, 510, 13, 51256], "temperature": 1.0, "avg_logprob": -0.9763990548940805, "compression_ratio": 2.6940298507462686, "no_speech_prob": 0.0009540353785268962}, {"id": 94, "seek": 11796, "start": 135.78, "end": 136.66, "text": " Ha ha.", "tokens": [51256, 4064, 324, 13, 51300], "temperature": 1.0, "avg_logprob": -0.9763990548940805, "compression_ratio": 2.6940298507462686, "no_speech_prob": 0.0009540353785268962}, {"id": 95, "seek": 11796, "start": 136.66, "end": 138.68, "text": " We have some scars.", "tokens": [51300, 492, 362, 512, 31353, 13, 51401], "temperature": 1.0, "avg_logprob": -0.9763990548940805, "compression_ratio": 2.6940298507462686, "no_speech_prob": 0.0009540353785268962}, {"id": 96, "seek": 11796, "start": 138.68, "end": 139.44, "text": " But I'm here.", "tokens": [51401, 583, 286, 478, 510, 13, 51439], "temperature": 1.0, "avg_logprob": -0.9763990548940805, "compression_ratio": 2.6940298507462686, "no_speech_prob": 0.0009540353785268962}, {"id": 97, "seek": 11796, "start": 139.48, "end": 141.95999999999998, "text": " I am here.", "tokens": [51441, 286, 669, 510, 13, 51565], "temperature": 1.0, "avg_logprob": -0.9763990548940805, "compression_ratio": 2.6940298507462686, "no_speech_prob": 0.0009540353785268962}, {"id": 98, "seek": 11796, "start": 142.51999999999998, "end": 143.56, "text": " Circumstances.", "tokens": [51593, 28938, 449, 372, 2676, 13, 51645], "temperature": 1.0, "avg_logprob": -0.9763990548940805, "compression_ratio": 2.6940298507462686, "no_speech_prob": 0.0009540353785268962}, {"id": 99, "seek": 11796, "start": 143.56, "end": 144.79999999999998, "text": " Some circumstances.", "tokens": [51645, 2188, 9121, 13, 51707], "temperature": 1.0, "avg_logprob": -0.9763990548940805, "compression_ratio": 2.6940298507462686, "no_speech_prob": 0.0009540353785268962}, {"id": 100, "seek": 11796, "start": 144.82, "end": 146.01999999999998, "text": " I'm still here.", "tokens": [51708, 286, 478, 920, 510, 13, 51768], "temperature": 1.0, "avg_logprob": -0.9763990548940805, "compression_ratio": 2.6940298507462686, "no_speech_prob": 0.0009540353785268962}, {"id": 101, "seek": 11796, "start": 146.01999999999998, "end": 147.06, "text": " But I'm still here.", "tokens": [51768, 583, 286, 478, 920, 510, 13, 51820], "temperature": 1.0, "avg_logprob": -0.9763990548940805, "compression_ratio": 2.6940298507462686, "no_speech_prob": 0.0009540353785268962}, {"id": 102, "seek": 11796, "start": 147.06, "end": 147.6, "text": " Disappointment.", "tokens": [51820, 4208, 1746, 3600, 518, 13, 51847], "temperature": 1.0, "avg_logprob": -0.9763990548940805, "compression_ratio": 2.6940298507462686, "no_speech_prob": 0.0009540353785268962}, {"id": 103, "seek": 14760, "start": 147.6, "end": 150.34, "text": " Oh, many disappointments.", "tokens": [50365, 876, 11, 867, 8505, 1117, 13, 50502], "temperature": 0.0, "avg_logprob": -0.6390251337095748, "compression_ratio": 1.5916666666666666, "no_speech_prob": 0.6194958090782166}, {"id": 104, "seek": 14760, "start": 151.04, "end": 151.96, "text": " Let's take it out.", "tokens": [50537, 961, 311, 747, 309, 484, 13, 50583], "temperature": 0.0, "avg_logprob": -0.6390251337095748, "compression_ratio": 1.5916666666666666, "no_speech_prob": 0.6194958090782166}, {"id": 105, "seek": 14760, "start": 155.07999999999998, "end": 155.32, "text": " Oh.", "tokens": [50739, 876, 13, 50751], "temperature": 0.0, "avg_logprob": -0.6390251337095748, "compression_ratio": 1.5916666666666666, "no_speech_prob": 0.6194958090782166}, {"id": 106, "seek": 14760, "start": 158.1, "end": 160.14, "text": " I am here.", "tokens": [50890, 286, 669, 510, 13, 50992], "temperature": 0.0, "avg_logprob": -0.6390251337095748, "compression_ratio": 1.5916666666666666, "no_speech_prob": 0.6194958090782166}, {"id": 107, "seek": 14760, "start": 161.76, "end": 162.78, "text": " Say that again, y'all.", "tokens": [51073, 6463, 300, 797, 11, 288, 6, 336, 13, 51124], "temperature": 0.0, "avg_logprob": -0.6390251337095748, "compression_ratio": 1.5916666666666666, "no_speech_prob": 0.6194958090782166}, {"id": 108, "seek": 14760, "start": 163.26, "end": 165.22, "text": " I am here.", "tokens": [51148, 286, 669, 510, 13, 51246], "temperature": 0.0, "avg_logprob": -0.6390251337095748, "compression_ratio": 1.5916666666666666, "no_speech_prob": 0.6194958090782166}, {"id": 109, "seek": 14760, "start": 166.12, "end": 167.12, "text": " With his stripes.", "tokens": [51291, 2022, 702, 27308, 13, 51341], "temperature": 0.0, "avg_logprob": -0.6390251337095748, "compression_ratio": 1.5916666666666666, "no_speech_prob": 0.6194958090782166}, {"id": 110, "seek": 14760, "start": 167.74, "end": 168.9, "text": " With his stripes.", "tokens": [51372, 2022, 702, 27308, 13, 51430], "temperature": 0.0, "avg_logprob": -0.6390251337095748, "compression_ratio": 1.5916666666666666, "no_speech_prob": 0.6194958090782166}, {"id": 111, "seek": 14760, "start": 168.9, "end": 171.51999999999998, "text": " I am here.", "tokens": [51430, 286, 669, 510, 13, 51561], "temperature": 0.0, "avg_logprob": -0.6390251337095748, "compression_ratio": 1.5916666666666666, "no_speech_prob": 0.6194958090782166}, {"id": 112, "seek": 14760, "start": 171.51999999999998, "end": 172.06, "text": " Hallelujah.", "tokens": [51561, 32359, 13, 51588], "temperature": 0.0, "avg_logprob": -0.6390251337095748, "compression_ratio": 1.5916666666666666, "no_speech_prob": 0.6194958090782166}, {"id": 113, "seek": 14760, "start": 172.06, "end": 172.35999999999999, "text": " Hallelujah.", "tokens": [51588, 32359, 13, 51603], "temperature": 0.0, "avg_logprob": -0.6390251337095748, "compression_ratio": 1.5916666666666666, "no_speech_prob": 0.6194958090782166}, {"id": 114, "seek": 14760, "start": 172.66, "end": 175.51999999999998, "text": " Oh, I am here.", "tokens": [51618, 876, 11, 286, 669, 510, 13, 51761], "temperature": 0.0, "avg_logprob": -0.6390251337095748, "compression_ratio": 1.5916666666666666, "no_speech_prob": 0.6194958090782166}, {"id": 115, "seek": 14760, "start": 175.54, "end": 177.07999999999998, "text": " Oh, oh, oh.", "tokens": [51762, 876, 11, 1954, 11, 1954, 13, 51839], "temperature": 0.0, "avg_logprob": -0.6390251337095748, "compression_ratio": 1.5916666666666666, "no_speech_prob": 0.6194958090782166}, {"id": 116, "seek": 17708, "start": 177.08, "end": 178.04000000000002, "text": " I'm here.", "tokens": [50365, 286, 478, 510, 13, 50413], "temperature": 0.0, "avg_logprob": -0.41692692598850606, "compression_ratio": 2.0657894736842106, "no_speech_prob": 0.0005111374775879085}, {"id": 117, "seek": 17708, "start": 178.74, "end": 180.58, "text": " I am here.", "tokens": [50448, 286, 669, 510, 13, 50540], "temperature": 0.0, "avg_logprob": -0.41692692598850606, "compression_ratio": 2.0657894736842106, "no_speech_prob": 0.0005111374775879085}, {"id": 118, "seek": 17708, "start": 180.60000000000002, "end": 183.12, "text": " Oh, anybody here like me?", "tokens": [50541, 876, 11, 4472, 510, 411, 385, 30, 50667], "temperature": 0.0, "avg_logprob": -0.41692692598850606, "compression_ratio": 2.0657894736842106, "no_speech_prob": 0.0005111374775879085}, {"id": 119, "seek": 17708, "start": 183.84, "end": 185.76000000000002, "text": " I am here.", "tokens": [50703, 286, 669, 510, 13, 50799], "temperature": 0.0, "avg_logprob": -0.41692692598850606, "compression_ratio": 2.0657894736842106, "no_speech_prob": 0.0005111374775879085}, {"id": 120, "seek": 17708, "start": 185.78, "end": 188.02, "text": " Oh, with his stripes.", "tokens": [50800, 876, 11, 365, 702, 27308, 13, 50912], "temperature": 0.0, "avg_logprob": -0.41692692598850606, "compression_ratio": 2.0657894736842106, "no_speech_prob": 0.0005111374775879085}, {"id": 121, "seek": 17708, "start": 188.34, "end": 189.38000000000002, "text": " With his stripes.", "tokens": [50928, 2022, 702, 27308, 13, 50980], "temperature": 0.0, "avg_logprob": -0.41692692598850606, "compression_ratio": 2.0657894736842106, "no_speech_prob": 0.0005111374775879085}, {"id": 122, "seek": 17708, "start": 189.4, "end": 190.20000000000002, "text": " I'm here.", "tokens": [50981, 286, 478, 510, 13, 51021], "temperature": 0.0, "avg_logprob": -0.41692692598850606, "compression_ratio": 2.0657894736842106, "no_speech_prob": 0.0005111374775879085}, {"id": 123, "seek": 17708, "start": 190.32000000000002, "end": 191.56, "text": " I am here.", "tokens": [51027, 286, 669, 510, 13, 51089], "temperature": 0.0, "avg_logprob": -0.41692692598850606, "compression_ratio": 2.0657894736842106, "no_speech_prob": 0.0005111374775879085}, {"id": 124, "seek": 17708, "start": 191.56, "end": 192.4, "text": " I like this part.", "tokens": [51089, 286, 411, 341, 644, 13, 51131], "temperature": 0.0, "avg_logprob": -0.41692692598850606, "compression_ratio": 2.0657894736842106, "no_speech_prob": 0.0005111374775879085}, {"id": 125, "seek": 17708, "start": 192.46, "end": 193.14000000000001, "text": " I like this part.", "tokens": [51134, 286, 411, 341, 644, 13, 51168], "temperature": 0.0, "avg_logprob": -0.41692692598850606, "compression_ratio": 2.0657894736842106, "no_speech_prob": 0.0005111374775879085}, {"id": 126, "seek": 17708, "start": 193.16000000000003, "end": 194.46, "text": " We have some scars.", "tokens": [51169, 492, 362, 512, 31353, 13, 51234], "temperature": 0.0, "avg_logprob": -0.41692692598850606, "compression_ratio": 2.0657894736842106, "no_speech_prob": 0.0005111374775879085}, {"id": 127, "seek": 17708, "start": 194.46, "end": 195.3, "text": " Oh, yeah.", "tokens": [51234, 876, 11, 1338, 13, 51276], "temperature": 0.0, "avg_logprob": -0.41692692598850606, "compression_ratio": 2.0657894736842106, "no_speech_prob": 0.0005111374775879085}, {"id": 128, "seek": 17708, "start": 195.88000000000002, "end": 197.10000000000002, "text": " I am here.", "tokens": [51305, 286, 669, 510, 13, 51366], "temperature": 0.0, "avg_logprob": -0.41692692598850606, "compression_ratio": 2.0657894736842106, "no_speech_prob": 0.0005111374775879085}, {"id": 129, "seek": 17708, "start": 197.14000000000001, "end": 197.64000000000001, "text": " I'm here.", "tokens": [51368, 286, 478, 510, 13, 51393], "temperature": 0.0, "avg_logprob": -0.41692692598850606, "compression_ratio": 2.0657894736842106, "no_speech_prob": 0.0005111374775879085}, {"id": 130, "seek": 17708, "start": 198.64000000000001, "end": 199.4, "text": " Circumstances.", "tokens": [51443, 28938, 449, 372, 2676, 13, 51481], "temperature": 0.0, "avg_logprob": -0.41692692598850606, "compression_ratio": 2.0657894736842106, "no_speech_prob": 0.0005111374775879085}, {"id": 131, "seek": 17708, "start": 200.14000000000001, "end": 200.9, "text": " Circumstances.", "tokens": [51518, 28938, 449, 372, 2676, 13, 51556], "temperature": 0.0, "avg_logprob": -0.41692692598850606, "compression_ratio": 2.0657894736842106, "no_speech_prob": 0.0005111374775879085}, {"id": 132, "seek": 17708, "start": 200.9, "end": 202.08, "text": " I'm still here.", "tokens": [51556, 286, 478, 920, 510, 13, 51615], "temperature": 0.0, "avg_logprob": -0.41692692598850606, "compression_ratio": 2.0657894736842106, "no_speech_prob": 0.0005111374775879085}, {"id": 133, "seek": 17708, "start": 202.20000000000002, "end": 203.10000000000002, "text": " I'm still here.", "tokens": [51621, 286, 478, 920, 510, 13, 51666], "temperature": 0.0, "avg_logprob": -0.41692692598850606, "compression_ratio": 2.0657894736842106, "no_speech_prob": 0.0005111374775879085}, {"id": 134, "seek": 17708, "start": 203.78, "end": 204.42000000000002, "text": " Disappointed.", "tokens": [51700, 4208, 1746, 33041, 13, 51732], "temperature": 0.0, "avg_logprob": -0.41692692598850606, "compression_ratio": 2.0657894736842106, "no_speech_prob": 0.0005111374775879085}, {"id": 135, "seek": 17708, "start": 205.60000000000002, "end": 205.9, "text": " Many disappointments.", "tokens": [51791, 5126, 8505, 1117, 13, 51806], "temperature": 0.0, "avg_logprob": -0.41692692598850606, "compression_ratio": 2.0657894736842106, "no_speech_prob": 0.0005111374775879085}, {"id": 136, "seek": 17708, "start": 206.46, "end": 206.9, "text": " I am here.", "tokens": [51834, 286, 669, 510, 13, 51856], "temperature": 0.0, "avg_logprob": -0.41692692598850606, "compression_ratio": 2.0657894736842106, "no_speech_prob": 0.0005111374775879085}, {"id": 137, "seek": 20708, "start": 207.08, "end": 208.52, "text": " I am here.", "tokens": [50365, 286, 669, 510, 13, 50437], "temperature": 0.2, "avg_logprob": -0.4452227150521627, "compression_ratio": 2.2181818181818183, "no_speech_prob": 0.001892934087663889}, {"id": 138, "seek": 20708, "start": 208.52, "end": 210.12, "text": " They have some scars.", "tokens": [50437, 814, 362, 512, 31353, 13, 50517], "temperature": 0.2, "avg_logprob": -0.4452227150521627, "compression_ratio": 2.2181818181818183, "no_speech_prob": 0.001892934087663889}, {"id": 139, "seek": 20708, "start": 211.34, "end": 212.62, "text": " I am here.", "tokens": [50578, 286, 669, 510, 13, 50642], "temperature": 0.2, "avg_logprob": -0.4452227150521627, "compression_ratio": 2.2181818181818183, "no_speech_prob": 0.001892934087663889}, {"id": 140, "seek": 20708, "start": 212.62, "end": 213.56, "text": " Ah, ah.", "tokens": [50642, 2438, 11, 3716, 13, 50689], "temperature": 0.2, "avg_logprob": -0.4452227150521627, "compression_ratio": 2.2181818181818183, "no_speech_prob": 0.001892934087663889}, {"id": 141, "seek": 20708, "start": 213.56, "end": 215.56, "text": " Circumstances.", "tokens": [50689, 28938, 449, 372, 2676, 13, 50789], "temperature": 0.2, "avg_logprob": -0.4452227150521627, "compression_ratio": 2.2181818181818183, "no_speech_prob": 0.001892934087663889}, {"id": 142, "seek": 20708, "start": 215.56, "end": 216.46, "text": " Circumstances.", "tokens": [50789, 28938, 449, 372, 2676, 13, 50834], "temperature": 0.2, "avg_logprob": -0.4452227150521627, "compression_ratio": 2.2181818181818183, "no_speech_prob": 0.001892934087663889}, {"id": 143, "seek": 20708, "start": 216.46, "end": 217.9, "text": " I'm still here.", "tokens": [50834, 286, 478, 920, 510, 13, 50906], "temperature": 0.2, "avg_logprob": -0.4452227150521627, "compression_ratio": 2.2181818181818183, "no_speech_prob": 0.001892934087663889}, {"id": 144, "seek": 20708, "start": 217.9, "end": 218.76000000000002, "text": " I'm still here.", "tokens": [50906, 286, 478, 920, 510, 13, 50949], "temperature": 0.2, "avg_logprob": -0.4452227150521627, "compression_ratio": 2.2181818181818183, "no_speech_prob": 0.001892934087663889}, {"id": 145, "seek": 20708, "start": 218.76000000000002, "end": 220.76000000000002, "text": " Disappointment.", "tokens": [50949, 4208, 1746, 3600, 518, 13, 51049], "temperature": 0.2, "avg_logprob": -0.4452227150521627, "compression_ratio": 2.2181818181818183, "no_speech_prob": 0.001892934087663889}, {"id": 146, "seek": 20708, "start": 220.76000000000002, "end": 221.60000000000002, "text": " Disappointments.", "tokens": [51049, 4208, 1746, 3600, 1117, 13, 51091], "temperature": 0.2, "avg_logprob": -0.4452227150521627, "compression_ratio": 2.2181818181818183, "no_speech_prob": 0.001892934087663889}, {"id": 147, "seek": 20708, "start": 221.60000000000002, "end": 222.62, "text": " I am here.", "tokens": [51091, 286, 669, 510, 13, 51142], "temperature": 0.2, "avg_logprob": -0.4452227150521627, "compression_ratio": 2.2181818181818183, "no_speech_prob": 0.001892934087663889}, {"id": 148, "seek": 20708, "start": 222.62, "end": 224.04000000000002, "text": " Oh, we're going to take it out this time.", "tokens": [51142, 876, 11, 321, 434, 516, 281, 747, 309, 484, 341, 565, 13, 51213], "temperature": 0.2, "avg_logprob": -0.4452227150521627, "compression_ratio": 2.2181818181818183, "no_speech_prob": 0.001892934087663889}, {"id": 149, "seek": 20708, "start": 224.04000000000002, "end": 227.4, "text": " Oh, I am here.", "tokens": [51213, 876, 11, 286, 669, 510, 13, 51381], "temperature": 0.2, "avg_logprob": -0.4452227150521627, "compression_ratio": 2.2181818181818183, "no_speech_prob": 0.001892934087663889}, {"id": 150, "seek": 20708, "start": 227.4, "end": 229.08, "text": " Oh, I'm here.", "tokens": [51381, 876, 11, 286, 478, 510, 13, 51465], "temperature": 0.2, "avg_logprob": -0.4452227150521627, "compression_ratio": 2.2181818181818183, "no_speech_prob": 0.001892934087663889}, {"id": 151, "seek": 20708, "start": 229.08, "end": 229.58, "text": " Yeah.", "tokens": [51465, 865, 13, 51490], "temperature": 0.2, "avg_logprob": -0.4452227150521627, "compression_ratio": 2.2181818181818183, "no_speech_prob": 0.001892934087663889}, {"id": 152, "seek": 20708, "start": 229.58, "end": 232.14000000000001, "text": " I am here.", "tokens": [51490, 286, 669, 510, 13, 51618], "temperature": 0.2, "avg_logprob": -0.4452227150521627, "compression_ratio": 2.2181818181818183, "no_speech_prob": 0.001892934087663889}, {"id": 153, "seek": 20708, "start": 232.14000000000001, "end": 233.44, "text": " Y'all better say it like you mean it.", "tokens": [51618, 398, 6, 336, 1101, 584, 309, 411, 291, 914, 309, 13, 51683], "temperature": 0.2, "avg_logprob": -0.4452227150521627, "compression_ratio": 2.2181818181818183, "no_speech_prob": 0.001892934087663889}, {"id": 154, "seek": 20708, "start": 233.44, "end": 234.34, "text": " Say it like you mean it.", "tokens": [51683, 6463, 309, 411, 291, 914, 309, 13, 51728], "temperature": 0.2, "avg_logprob": -0.4452227150521627, "compression_ratio": 2.2181818181818183, "no_speech_prob": 0.001892934087663889}, {"id": 155, "seek": 20708, "start": 234.34, "end": 235.14000000000001, "text": " Say it like you mean it.", "tokens": [51728, 6463, 309, 411, 291, 914, 309, 13, 51768], "temperature": 0.2, "avg_logprob": -0.4452227150521627, "compression_ratio": 2.2181818181818183, "no_speech_prob": 0.001892934087663889}, {"id": 156, "seek": 20708, "start": 235.14000000000001, "end": 235.84, "text": " I am here.", "tokens": [51768, 286, 669, 510, 13, 51803], "temperature": 0.2, "avg_logprob": -0.4452227150521627, "compression_ratio": 2.2181818181818183, "no_speech_prob": 0.001892934087663889}, {"id": 157, "seek": 20708, "start": 235.84, "end": 236.42000000000002, "text": " I am here.", "tokens": [51803, 286, 669, 510, 13, 51832], "temperature": 0.2, "avg_logprob": -0.4452227150521627, "compression_ratio": 2.2181818181818183, "no_speech_prob": 0.001892934087663889}, {"id": 158, "seek": 20708, "start": 236.42000000000002, "end": 236.92000000000002, "text": " I am here.", "tokens": [51832, 286, 669, 510, 13, 51857], "temperature": 0.2, "avg_logprob": -0.4452227150521627, "compression_ratio": 2.2181818181818183, "no_speech_prob": 0.001892934087663889}, {"id": 159, "seek": 23692, "start": 236.92, "end": 238.16, "text": " I am here.", "tokens": [50365, 286, 669, 510, 13, 50427], "temperature": 0.0, "avg_logprob": -0.370240235940004, "compression_ratio": 2.0140845070422535, "no_speech_prob": 0.007292173337191343}, {"id": 160, "seek": 23692, "start": 238.16, "end": 239.51999999999998, "text": " With his stripes.", "tokens": [50427, 2022, 702, 27308, 13, 50495], "temperature": 0.0, "avg_logprob": -0.370240235940004, "compression_ratio": 2.0140845070422535, "no_speech_prob": 0.007292173337191343}, {"id": 161, "seek": 23692, "start": 239.51999999999998, "end": 240.76, "text": " With his stripes.", "tokens": [50495, 2022, 702, 27308, 13, 50557], "temperature": 0.0, "avg_logprob": -0.370240235940004, "compression_ratio": 2.0140845070422535, "no_speech_prob": 0.007292173337191343}, {"id": 162, "seek": 23692, "start": 240.76, "end": 243.51999999999998, "text": " I am here.", "tokens": [50557, 286, 669, 510, 13, 50695], "temperature": 0.0, "avg_logprob": -0.370240235940004, "compression_ratio": 2.0140845070422535, "no_speech_prob": 0.007292173337191343}, {"id": 163, "seek": 23692, "start": 243.51999999999998, "end": 244.72, "text": " And the cross died.", "tokens": [50695, 400, 264, 3278, 4539, 13, 50755], "temperature": 0.0, "avg_logprob": -0.370240235940004, "compression_ratio": 2.0140845070422535, "no_speech_prob": 0.007292173337191343}, {"id": 164, "seek": 23692, "start": 244.72, "end": 247.54, "text": " Oh, I am here.", "tokens": [50755, 876, 11, 286, 669, 510, 13, 50896], "temperature": 0.0, "avg_logprob": -0.370240235940004, "compression_ratio": 2.0140845070422535, "no_speech_prob": 0.007292173337191343}, {"id": 165, "seek": 23692, "start": 247.54, "end": 250.44, "text": " Oh, he died that we might be healed.", "tokens": [50896, 876, 11, 415, 4539, 300, 321, 1062, 312, 20482, 13, 51041], "temperature": 0.0, "avg_logprob": -0.370240235940004, "compression_ratio": 2.0140845070422535, "no_speech_prob": 0.007292173337191343}, {"id": 166, "seek": 23692, "start": 250.44, "end": 252.45999999999998, "text": " I am here.", "tokens": [51041, 286, 669, 510, 13, 51142], "temperature": 0.0, "avg_logprob": -0.370240235940004, "compression_ratio": 2.0140845070422535, "no_speech_prob": 0.007292173337191343}, {"id": 167, "seek": 23692, "start": 252.45999999999998, "end": 255.54, "text": " Oh, he suffered that we might be healed.", "tokens": [51142, 876, 11, 415, 12770, 300, 321, 1062, 312, 20482, 13, 51296], "temperature": 0.0, "avg_logprob": -0.370240235940004, "compression_ratio": 2.0140845070422535, "no_speech_prob": 0.007292173337191343}, {"id": 168, "seek": 23692, "start": 255.54, "end": 257.5, "text": " I am here.", "tokens": [51296, 286, 669, 510, 13, 51394], "temperature": 0.0, "avg_logprob": -0.370240235940004, "compression_ratio": 2.0140845070422535, "no_speech_prob": 0.007292173337191343}, {"id": 169, "seek": 23692, "start": 257.5, "end": 259.3, "text": " Ah, ah, ah.", "tokens": [51394, 2438, 11, 3716, 11, 3716, 13, 51484], "temperature": 0.0, "avg_logprob": -0.370240235940004, "compression_ratio": 2.0140845070422535, "no_speech_prob": 0.007292173337191343}, {"id": 170, "seek": 23692, "start": 259.3, "end": 260.3, "text": " From the inside out.", "tokens": [51484, 3358, 264, 1854, 484, 13, 51534], "temperature": 0.0, "avg_logprob": -0.370240235940004, "compression_ratio": 2.0140845070422535, "no_speech_prob": 0.007292173337191343}, {"id": 171, "seek": 23692, "start": 260.3, "end": 261.94, "text": " With his stripes.", "tokens": [51534, 2022, 702, 27308, 13, 51616], "temperature": 0.0, "avg_logprob": -0.370240235940004, "compression_ratio": 2.0140845070422535, "no_speech_prob": 0.007292173337191343}, {"id": 172, "seek": 23692, "start": 261.94, "end": 263.91999999999996, "text": " I am here.", "tokens": [51616, 286, 669, 510, 13, 51715], "temperature": 0.0, "avg_logprob": -0.370240235940004, "compression_ratio": 2.0140845070422535, "no_speech_prob": 0.007292173337191343}, {"id": 173, "seek": 23692, "start": 263.91999999999996, "end": 265.03999999999996, "text": " Oh, yeah.", "tokens": [51715, 876, 11, 1338, 13, 51771], "temperature": 0.0, "avg_logprob": -0.370240235940004, "compression_ratio": 2.0140845070422535, "no_speech_prob": 0.007292173337191343}, {"id": 174, "seek": 23692, "start": 265.03999999999996, "end": 266.28, "text": " They have some scars.", "tokens": [51771, 814, 362, 512, 31353, 13, 51833], "temperature": 0.0, "avg_logprob": -0.370240235940004, "compression_ratio": 2.0140845070422535, "no_speech_prob": 0.007292173337191343}, {"id": 175, "seek": 26628, "start": 266.28, "end": 266.88, "text": " God.", "tokens": [50365, 1265, 13, 50395], "temperature": 1.0, "avg_logprob": -0.8940520322412476, "compression_ratio": 1.8231707317073171, "no_speech_prob": 0.00047597725642845035}, {"id": 176, "seek": 26628, "start": 266.88, "end": 267.71999999999997, "text": " Ah.", "tokens": [50395, 2438, 13, 50437], "temperature": 1.0, "avg_logprob": -0.8940520322412476, "compression_ratio": 1.8231707317073171, "no_speech_prob": 0.00047597725642845035}, {"id": 177, "seek": 26628, "start": 267.71999999999997, "end": 269.53999999999996, "text": " I am here.", "tokens": [50437, 286, 669, 510, 13, 50528], "temperature": 1.0, "avg_logprob": -0.8940520322412476, "compression_ratio": 1.8231707317073171, "no_speech_prob": 0.00047597725642845035}, {"id": 178, "seek": 26628, "start": 269.53999999999996, "end": 270.08, "text": " Circumstances.", "tokens": [50528, 28938, 449, 372, 2676, 13, 50555], "temperature": 1.0, "avg_logprob": -0.8940520322412476, "compression_ratio": 1.8231707317073171, "no_speech_prob": 0.00047597725642845035}, {"id": 179, "seek": 26628, "start": 270.08, "end": 272.65999999999997, "text": " Bad love to Johnathan Nelson and Purpose.", "tokens": [50555, 11523, 959, 281, 2619, 9390, 23857, 293, 14682, 43501, 13, 50684], "temperature": 1.0, "avg_logprob": -0.8940520322412476, "compression_ratio": 1.8231707317073171, "no_speech_prob": 0.00047597725642845035}, {"id": 180, "seek": 26628, "start": 272.65999999999997, "end": 274.41999999999996, "text": " Y'all bless them.", "tokens": [50684, 398, 6, 336, 5227, 552, 13, 50772], "temperature": 1.0, "avg_logprob": -0.8940520322412476, "compression_ratio": 1.8231707317073171, "no_speech_prob": 0.00047597725642845035}, {"id": 181, "seek": 26628, "start": 274.41999999999996, "end": 275.65999999999997, "text": " I'm still here.", "tokens": [50772, 286, 478, 920, 510, 13, 50834], "temperature": 1.0, "avg_logprob": -0.8940520322412476, "compression_ratio": 1.8231707317073171, "no_speech_prob": 0.00047597725642845035}, {"id": 182, "seek": 26628, "start": 275.65999999999997, "end": 277.41999999999996, "text": " Disapointment.", "tokens": [50834, 4208, 569, 3600, 518, 13, 50922], "temperature": 1.0, "avg_logprob": -0.8940520322412476, "compression_ratio": 1.8231707317073171, "no_speech_prob": 0.00047597725642845035}, {"id": 183, "seek": 26628, "start": 277.41999999999996, "end": 278.0, "text": " That's right.", "tokens": [50922, 663, 311, 558, 13, 50951], "temperature": 1.0, "avg_logprob": -0.8940520322412476, "compression_ratio": 1.8231707317073171, "no_speech_prob": 0.00047597725642845035}, {"id": 184, "seek": 26628, "start": 278.0, "end": 279.4, "text": " I am here.", "tokens": [50951, 286, 669, 510, 13, 51021], "temperature": 1.0, "avg_logprob": -0.8940520322412476, "compression_ratio": 1.8231707317073171, "no_speech_prob": 0.00047597725642845035}, {"id": 185, "seek": 26628, "start": 279.4, "end": 280.41999999999996, "text": " Say that again.", "tokens": [51021, 6463, 300, 797, 13, 51072], "temperature": 1.0, "avg_logprob": -0.8940520322412476, "compression_ratio": 1.8231707317073171, "no_speech_prob": 0.00047597725642845035}, {"id": 186, "seek": 26628, "start": 280.41999999999996, "end": 283.15999999999997, "text": " They have some scars.", "tokens": [51072, 814, 362, 512, 31353, 13, 51209], "temperature": 1.0, "avg_logprob": -0.8940520322412476, "compression_ratio": 1.8231707317073171, "no_speech_prob": 0.00047597725642845035}, {"id": 187, "seek": 26628, "start": 283.15999999999997, "end": 285.41999999999996, "text": " I am here.", "tokens": [51209, 286, 669, 510, 13, 51322], "temperature": 1.0, "avg_logprob": -0.8940520322412476, "compression_ratio": 1.8231707317073171, "no_speech_prob": 0.00047597725642845035}, {"id": 188, "seek": 26628, "start": 285.41999999999996, "end": 287.91999999999996, "text": " Circumstances.", "tokens": [51322, 28938, 449, 372, 2676, 13, 51447], "temperature": 1.0, "avg_logprob": -0.8940520322412476, "compression_ratio": 1.8231707317073171, "no_speech_prob": 0.00047597725642845035}, {"id": 189, "seek": 26628, "start": 287.91999999999996, "end": 290.58, "text": " I'm still here.", "tokens": [51447, 286, 478, 920, 510, 13, 51580], "temperature": 1.0, "avg_logprob": -0.8940520322412476, "compression_ratio": 1.8231707317073171, "no_speech_prob": 0.00047597725642845035}, {"id": 190, "seek": 26628, "start": 290.58, "end": 293.58, "text": " Disappointment.", "tokens": [51580, 4208, 1746, 3600, 518, 13, 51730], "temperature": 1.0, "avg_logprob": -0.8940520322412476, "compression_ratio": 1.8231707317073171, "no_speech_prob": 0.00047597725642845035}, {"id": 191, "seek": 26628, "start": 293.58, "end": 294.08, "text": " I am here!", "tokens": [51730, 286, 669, 510, 0, 51755], "temperature": 1.0, "avg_logprob": -0.8940520322412476, "compression_ratio": 1.8231707317073171, "no_speech_prob": 0.00047597725642845035}, {"id": 192, "seek": 26628, "start": 294.08, "end": 294.67999999999995, "text": " I am here.", "tokens": [51755, 286, 669, 510, 13, 51785], "temperature": 1.0, "avg_logprob": -0.8940520322412476, "compression_ratio": 1.8231707317073171, "no_speech_prob": 0.00047597725642845035}, {"id": 193, "seek": 26628, "start": 294.67999999999995, "end": 295.38, "text": " He have some scars.", "tokens": [51785, 634, 362, 512, 31353, 13, 51820], "temperature": 1.0, "avg_logprob": -0.8940520322412476, "compression_ratio": 1.8231707317073171, "no_speech_prob": 0.00047597725642845035}, {"id": 194, "seek": 26628, "start": 295.38, "end": 295.88, "text": " I am here.", "tokens": [51820, 286, 669, 510, 13, 51845], "temperature": 1.0, "avg_logprob": -0.8940520322412476, "compression_ratio": 1.8231707317073171, "no_speech_prob": 0.00047597725642845035}, {"id": 195, "seek": 29628, "start": 296.28, "end": 326.26, "text": " Thank you.", "tokens": [50365, 1044, 291, 13, 51864], "temperature": 0.0, "avg_logprob": -0.26742392778396606, "compression_ratio": 0.5555555555555556, "no_speech_prob": 0.8394528031349182}], "language": "en"}